qr_vision_service/__init__.py
qr_vision_service/cli.py
qr_vision_service/service.py
qr_vision_service/vision.jar
qr_vision_service-1.0.0.dist-info/licenses/LICENSE
qr_vision_service-1.0.0.dist-info/METADATA
qr_vision_service-1.0.0.dist-info/WHEEL
qr_vision_service-1.0.0.dist-info/entry_points.txt
qr_vision_service-1.0.0.dist-info/top_level.txt
qr_vision_service-1.0.0.dist-info/RECORD
