Metadata-Version: 2.4
Name: qr-vision-service
Version: 1.0.0
Summary: Comprehensive QR Code & Barcode Service with region detection and multi-engine support
Author-email: QR Vision <dnt.doanngocthanh@gmail.com>
License-Expression: MIT
Project-URL: Homepage, https://github.com/k23doanngocthanh/vision
Project-URL: Repository, https://github.com/k23doanngocthanh/vision
Project-URL: Documentation, https://github.com/k23doanngocthanh/vision#readme
Project-URL: Issues, https://github.com/k23doanngocthanh/vision/issues
Keywords: qr,qrcode,barcode,vision,detection,region,zxing,boofcv
Classifier: Development Status :: 5 - Production/Stable
Classifier: Intended Audience :: Developers
Classifier: Operating System :: OS Independent
Classifier: Programming Language :: Python :: 3
Classifier: Programming Language :: Python :: 3.7
Classifier: Programming Language :: Python :: 3.8
Classifier: Programming Language :: Python :: 3.9
Classifier: Programming Language :: Python :: 3.10
Classifier: Programming Language :: Python :: 3.11
Classifier: Programming Language :: Python :: 3.12
Classifier: Topic :: Software Development :: Libraries :: Python Modules
Classifier: Topic :: Multimedia :: Graphics :: Graphics Conversion
Classifier: Topic :: Scientific/Engineering :: Image Recognition
Requires-Python: >=3.7
License-File: LICENSE
Requires-Dist: pillow>=8.0.0
Provides-Extra: dev
Requires-Dist: pytest>=6.0; extra == "dev"
Requires-Dist: pytest-cov; extra == "dev"
Requires-Dist: black; extra == "dev"
Requires-Dist: flake8; extra == "dev"
Requires-Dist: mypy; extra == "dev"
Dynamic: license-file
